[
  {
    "id": "1776525193229-r5wzkx",
    "type": "lesson",
    "name": "Fixed extension & persona bugs",
    "summary": "Resolved aggressive interview extension triggers and cross-session persona switch persistence.",
    "detail": "Previously, the interview extension triggered too aggressively and persona switches didn't persist across sessions. Both were identified and fixed, indicating stability in these areas now.",
    "content": "Previously, the interview extension triggered too aggressively and persona switches didn't persist across sessions. Both were identified and fixed, indicating stability in these areas now.",
    "tags": [
      "fixed",
      "extension",
      "persona",
      "bugs",
      "resolved",
      "aggressive",
      "interview",
      "triggers",
      "and",
      "cross-session",
      "switch",
      "persistence.",
      "previously",
      "the",
      "triggered",
      "too",
      "aggressively",
      "switches",
      "didn",
      "persist",
      "across",
      "sessions.",
      "both",
      "were",
      "identified",
      "indicating",
      "stability",
      "in",
      "these",
      "areas"
    ],
    "project": "tmp/np-exp-run-001-control",
    "importance": 8,
    "strength": 90,
    "created": "2026-04-18T15:13:13.229Z",
    "eventTime": "2026-04-18T15:13:13.229Z",
    "accessCount": 0,
    "relatedIds": [],
    "retention": "key-event",
    "salience": 8,
    "stability": "stable",
    "relations": []
  }
]